sphinxcontrib/__init__.py
sphinxcontrib/unicode_ids/unicode_ids.py
sphinxcontrib/unicode_ids/__init__.py
sphinxcontrib/unicode_ids/doc/conf.py
sphinxcontrib/unicode_ids/doc/index.rst
sphinxcontrib/unicode_ids/doc/make.bat
sphinxcontrib/unicode_ids/doc/Makefile
sphinxcontrib/unicode_ids/doc/module_document.rst
sphinxcontrib/unicode_ids/doc/README.rst
sphinxcontrib/unicode_ids/doc/README_ja.rst
sphinxcontrib/unicode_ids/doc/_build/html/index.html
sphinxcontrib/unicode_ids/doc/_build/html/module_document.html
sphinxcontrib/unicode_ids/doc/_build/html/objects.inv
sphinxcontrib/unicode_ids/doc/_build/html/README.html
sphinxcontrib/unicode_ids/doc/_build/html/README_ja.html
sphinxcontrib/unicode_ids/doc/_build/html/search.html
sphinxcontrib/unicode_ids/doc/_build/html/searchindex.js
sphinxcontrib/unicode_ids/doc/_build/html/_sources/index.txt
sphinxcontrib/unicode_ids/doc/_build/html/_sources/module_document.txt
sphinxcontrib/unicode_ids/doc/_build/html/_sources/README.txt
sphinxcontrib/unicode_ids/doc/_build/html/_sources/README_ja.txt
sphinxcontrib/unicode_ids/doc/_build/html/_static/ajax-loader.gif
sphinxcontrib/unicode_ids/doc/_build/html/_static/alert_info_32.png
sphinxcontrib/unicode_ids/doc/_build/html/_static/alert_warning_32.png
sphinxcontrib/unicode_ids/doc/_build/html/_static/basic.css
sphinxcontrib/unicode_ids/doc/_build/html/_static/bg-page.png
sphinxcontrib/unicode_ids/doc/_build/html/_static/bullet_orange.png
sphinxcontrib/unicode_ids/doc/_build/html/_static/comment-bright.png
sphinxcontrib/unicode_ids/doc/_build/html/_static/comment-close.png
sphinxcontrib/unicode_ids/doc/_build/html/_static/comment.png
sphinxcontrib/unicode_ids/doc/_build/html/_static/doctools.js
sphinxcontrib/unicode_ids/doc/_build/html/_static/down-pressed.png
sphinxcontrib/unicode_ids/doc/_build/html/_static/down.png
sphinxcontrib/unicode_ids/doc/_build/html/_static/file.png
sphinxcontrib/unicode_ids/doc/_build/html/_static/haiku.css
unicode_ids-2.0.5.dist-info/DESCRIPTION.rst
unicode_ids-2.0.5.dist-info/METADATA
unicode_ids-2.0.5.dist-info/metadata.json
unicode_ids-2.0.5.dist-info/RECORD
unicode_ids-2.0.5.dist-info/top_level.txt
unicode_ids-2.0.5.dist-info/WHEEL
